cloudflare-ai/__init__.py
cloudflare-ai/core.py
cloudflare-ai/errors.py
cloudflare-ai/models.py
cloudflare_ai/__init__.py
cloudflare_ai/core.py
cloudflare_ai/errors.py
cloudflare_ai/models.py
cloudflare_ai-0.0.6.dist-info/LICENSE
cloudflare_ai-0.0.6.dist-info/METADATA
cloudflare_ai-0.0.6.dist-info/WHEEL
cloudflare_ai-0.0.6.dist-info/top_level.txt
cloudflare_ai-0.0.6.dist-info/RECORD
