Metadata-Version: 2.1
Name: cloudflare-ai
Version: 0.0.6
Summary: Cloudflare AI Python SDK
Home-page: https://github.com/alexraskin/cloudflare-ai-py
Author: alexraskin
Author-email: <root@alexraskin.com>
License: MIT License
Keywords: module,Cloudflare,library,package,python,CloudflareAI
Classifier: Programming Language :: Python
Classifier: Programming Language :: Python :: 3.10
License-File: LICENSE
Requires-Dist: httpx
Requires-Dist: aiofiles
Requires-Dist: starlette
